Metadata-Version: 1.0
Name: Bibekdistribution
Version: 0.1
Summary: Gaussian and Binary distributions
Home-page: UNKNOWN
Author: Bibek Shah Shankhar
Author-email: shahshankharbibek@gmail.com
License: UNKNOWN
Platform: UNKNOWN
